pyHIARD/__init__.py
pyHIARD/common_functions.py
pyHIARD/constants.py
pyHIARD/main.py
pyHIARD/AGC/AGC.py
pyHIARD/AGC/__init__.py
pyHIARD/AGC/base_galaxies.py
pyHIARD/ROC/ROC.py
pyHIARD/ROC/__init__.py
pyHIARD/Resources/__init__.py
pyHIARD/Resources/Cubes/Data_Cubes_Info.txt
pyHIARD/Resources/Cubes/__init__.py
pyHIARD/Resources/Cubes/Circinus/Circinus.py
pyHIARD/Resources/Cubes/Circinus/Circinus.rotcur
pyHIARD/Resources/Cubes/Circinus/__init__.py
pyHIARD/Resources/Cubes/ESO_223_G009/ESO_223_G009.py
pyHIARD/Resources/Cubes/ESO_223_G009/ESO_223_G009.rotcur
pyHIARD/Resources/Cubes/ESO_223_G009/__init__.py
pyHIARD/Resources/Cubes/M_83/M_83.py
pyHIARD/Resources/Cubes/M_83/M_83.rotcur
pyHIARD/Resources/Cubes/M_83/__init__.py
pyHIARD/Resources/Cubes/NGC_2903/NGC_2903.def
pyHIARD/Resources/Cubes/NGC_2903/NGC_2903.py
pyHIARD/Resources/Cubes/NGC_2903/__init__.py
pyHIARD/Resources/Cubes/NGC_3198/NGC_3198.def
pyHIARD/Resources/Cubes/NGC_3198/NGC_3198.py
pyHIARD/Resources/Cubes/NGC_3198/NGC_3198_Original.def
pyHIARD/Resources/Cubes/NGC_3198/__init__.py
pyHIARD/Resources/Cubes/NGC_5023/NGC_5023.def
pyHIARD/Resources/Cubes/NGC_5023/NGC_5023.py
pyHIARD/Resources/Cubes/NGC_5023/__init__.py
pyHIARD/Resources/Cubes/NGC_5204/NGC_5204.def
pyHIARD/Resources/Cubes/NGC_5204/NGC_5204.py
pyHIARD/Resources/Cubes/NGC_5204/__init__.py
pyHIARD/Resources/Cubes/UGC_1281/UGC_1281.def
pyHIARD/Resources/Cubes/UGC_1281/UGC_1281.py
pyHIARD/Resources/Cubes/UGC_1281/__init__.py
pyHIARD/Resources/Cubes/UGC_7774/UGC_7774.def
pyHIARD/Resources/Cubes/UGC_7774/UGC_7774.py
pyHIARD/Resources/Cubes/UGC_7774/__init__.py
pyHIARD/Templates/Sofia_Template.par
pyHIARD/Templates/Template.def
pyHIARD/Templates/Template_Header.py
pyHIARD/Templates/__init__.py
pyHIARD/Templates/roc_galaxy_template.py
pyHIARD/conf/__init__.py
pyHIARD/conf/config.py
pyhiard-1.2.3.dist-info/METADATA
pyhiard-1.2.3.dist-info/WHEEL
pyhiard-1.2.3.dist-info/entry_points.txt
pyhiard-1.2.3.dist-info/licenses/LICENSE
pyhiard-1.2.3.dist-info/RECORD
