Metadata-Version: 2.4
Name: pyHIARD
Version: 1.2.3
Summary: Development Status :: 4 - Beta
Project-URL: Homepage, https://github.com/PeterKamphuis/pyHIARD
Author-email: "P. Kamphuis" <peterkamphuisastronomy@gmail.com>
License-Expression: GPL-3.0-or-later
License-File: LICENSE
Classifier: Development Status :: 5 - Production/Stable
Classifier: Intended Audience :: Science/Research
Classifier: License :: OSI Approved :: GNU General Public License v3 (GPLv3)
Classifier: Operating System :: POSIX :: Linux
Classifier: Programming Language :: Python :: 3
Classifier: Topic :: Scientific/Engineering :: Astronomy
Requires-Python: >=3.6
Requires-Dist: astropy
Requires-Dist: casadata; python_version >= '3.10'
Requires-Dist: casatasks; python_version >= '3.10'
Requires-Dist: future-fstrings
Requires-Dist: importlib-metadata
Requires-Dist: importlib-resources>=3.3.0; python_version < '3.7'
Requires-Dist: matplotlib
Requires-Dist: numpy>=1.14
Requires-Dist: omegaconf>=2.2.2
Requires-Dist: psutil
Requires-Dist: scipy>1.6.0
